auto_mind/__init__.py
auto_mind/supervised/__init__.py
auto_mind/supervised/_action.py
auto_mind/supervised/_action_data.py
auto_mind/supervised/_action_handlers.py
auto_mind/supervised/_base_runner.py
auto_mind/supervised/_batch_handler.py
auto_mind/supervised/_dataset.py
auto_mind/supervised/_manager.py
auto_mind/supervised/_state_handler.py
auto_mind/supervised/data.py
auto_mind/supervised/handlers.py
auto_mind-0.3.2.dist-info/METADATA
auto_mind-0.3.2.dist-info/WHEEL
auto_mind-0.3.2.dist-info/licenses/LICENSE
auto_mind-0.3.2.dist-info/RECORD
