Metadata-Version: 2.3
Name: auto_mind
Version: 0.3.2
Summary: AutoMind: A Comprehensive Machine Learning Library
Project-URL: Homepage, https://github.com/lucasbasquerotto/auto-mind
Project-URL: Issues, https://github.com/lucasbasquerotto/auto-mind/issues
Author-email: Lucas Basquerotto <lucasbasquerotto@gmail.com>
License-File: LICENSE
Classifier: License :: OSI Approved :: MIT License
Classifier: Operating System :: OS Independent
Classifier: Programming Language :: Python :: 3
Requires-Python: >=3.8
